README.txt
setup.cfg
setup.py
adi/__init__.py
adi.suite.egg-info/PKG-INFO
adi.suite.egg-info/SOURCES.txt
adi.suite.egg-info/dependency_links.txt
adi.suite.egg-info/entry_points.txt
adi.suite.egg-info/namespace_packages.txt
adi.suite.egg-info/not-zip-safe
adi.suite.egg-info/paster_plugins.txt
adi.suite.egg-info/requires.txt
adi.suite.egg-info/top_level.txt
adi/suite/README.txt
adi/suite/__init__.py
adi/suite/config.py
adi/suite/configure.zcml
adi/suite/skins.zcml
adi/suite/browser/__init__.py
adi/suite/browser/adi_call_galleryview.pt
adi/suite/browser/adi_fancybox.png
adi/suite/browser/adi_suite.css
adi/suite/browser/adi_suite_content.pt
adi/suite/browser/adi_suite_flowplayer.pt
adi/suite/browser/adi_suite_galleryview.pt
adi/suite/browser/adi_suite_helper.py
adi/suite/browser/configure.zcml
adi/suite/browser/flowplayer-3.2.4.min.js
adi/suite/browser/play.png
adi/suite/content/__init__.py
adi/suite/content/configure.zcml
adi/suite/content/gallery.py
adi/suite/content/suite.py
adi/suite/interfaces/__init__.py
adi/suite/interfaces/gallery.py
adi/suite/interfaces/suite.py
adi/suite/profiles/default/cssregistry.xml
adi/suite/profiles/default/factorytool.xml
adi/suite/profiles/default/metadata.xml
adi/suite/profiles/default/portlets.xml
adi/suite/profiles/default/propertiestool.xml
adi/suite/profiles/default/rolemap.xml
adi/suite/profiles/default/skins.xml
adi/suite/profiles/default/types.xml
adi/suite/profiles/default/types/Folder.xml
adi/suite/profiles/default/types/Gallery.xml
adi/suite/profiles/default/types/Suite.xml
adi/suite/skins/adi_suite_files/flash.png
adi/suite/skins/adi_suite_files/flowplayer-3.2.5.swf
adi/suite/skins/adi_suite_files/flowplayer.audio-3.2.1.swf
adi/suite/skins/adi_suite_files/flowplayer.controls-3.2.3.swf
adi/suite/skins/adi_suite_files/movie.png
adi/suite/skins/adi_suite_files/noprev.png
adi/suite/skins/adi_suite_files/pic.png
adi/suite/tests/__init__.py
adi/suite/tests/base.py
adi/suite/tests/test_doctest.py
docs/HISTORY.txt
docs/INSTALL.txt
docs/LICENSE.GPL
docs/LICENSE.txt