Metadata-Version: 1.0
Name: adi.suite
Version: 0.6
Summary: A suite for javascript multimedia galleries.
Home-page: http://ida-ebkes.eu
Author: Ida Ebkes
Author-email: contact@ida-ebkes.eu
License: GPL
Platform: UNKNOWN
Classifier: Framework :: Plone
Classifier: Framework :: Plone :: 4.1
Classifier: Intended Audience :: System Administrators
Classifier: License :: OSI Approved :: GNU General Public License (GPL)
